pleiotropy/__init__.py
pleiotropy-0.1.1.dist-info/LICENSE
pleiotropy-0.1.1.dist-info/WHEEL
pleiotropy-0.1.1.dist-info/METADATA
pleiotropy-0.1.1.dist-info/RECORD
