Metadata-Version: 2.1
Name: pleiotropy
Version: 0.1.1
Summary: 
Author: jlikhuva
Author-email: jlikhuva@alumni.stanford.edu
Requires-Python: >=3.8,<4.0
Classifier: Programming Language :: Python :: 3
Classifier: Programming Language :: Python :: 3.10
Classifier: Programming Language :: Python :: 3.8
Classifier: Programming Language :: Python :: 3.9
